nhpgd/nomenclador.py
nhpgd_django/__init__.py
nhpgd_django/admin.py
nhpgd_django/apps.py
nhpgd_django/models.py
nhpgd_django/tests.py
nhpgd_django/views.py
nhpgd_django/migrations/0001_initial.py
nhpgd_django/migrations/__init__.py
nhpgd-0.205.dist-info/METADATA
nhpgd-0.205.dist-info/WHEEL
nhpgd-0.205.dist-info/top_level.txt
nhpgd-0.205.dist-info/RECORD
