Metadata-Version: 2.1
Name: nhpgd
Version: 0.205
Summary: Lista de Códigos del Nomenclador de Hospitales públicos de gestión descentralizada. Librería Python simple + versión Django
Home-page: https://github.com/cluster311/nhpgd
Author: Andres Vazquez
Author-email: andres@data99.com.ar
License: MIT
Platform: UNKNOWN
Classifier: Programming Language :: Python :: 3
Classifier: Programming Language :: Python :: 3.6
Classifier: License :: OSI Approved :: MIT License
Classifier: Framework :: Django
Classifier: Framework :: Django :: 2.2
Classifier: Operating System :: OS Independent
Classifier: Intended Audience :: Developers
Requires-Python: >=3.6
